mergedb/__init__.py
mergedb/__main__.py
mergedb/cli.py
mergedb/errors.py
mergedb/data_types/__init__.py
mergedb/data_types/database.py
mergedb/data_types/declaration.py
mergedb/data_types/directory.py
mergedb/data_types/tests/__init__.py
mergedb/data_types/tests/test_declarations.py
mergedb/merge_functions/__init__.py
mergedb/merge_functions/array.py
mergedb/merge_functions/array_merge.py
mergedb/merge_functions/deep_merge.py
mergedb/merge_functions/dict.py
mergedb/merge_functions/merge_controller.py
mergedb/merge_functions/simple_merge.py
mergedb/merge_functions/tests/__init__.py
mergedb/merge_functions/tests/test_deep_merge.py
mergedb/merge_functions/tests/test_deep_merge_controller.py
mergedb/merge_functions/tests/test_simple_merge.py
mergedb-0.0.6.dist-info/METADATA
mergedb-0.0.6.dist-info/WHEEL
mergedb-0.0.6.dist-info/entry_points.txt
mergedb-0.0.6.dist-info/top_level.txt
mergedb-0.0.6.dist-info/RECORD
