Metadata-Version: 2.1
Name: mergedb
Version: 0.0.6
Summary: UNKNOWN
Home-page: https://github.com/graysonhead/mergedb
Author: Grayson Head
Author-email: grayson@graysonhead.net
License: GPL V3
Platform: UNKNOWN
Requires-Dist: pyyaml (>=5.1.0)
Requires-Dist: colorama (>=0.4.1)
Requires-Dist: jinja2 (>=2.10.1)
Requires-Dist: pprint (>=0.1)
